pytest_scenario_files/__init__.py
pytest_scenario_files/plugin.py
pytest_scenario_files/py.typed
pytest_scenario_files-1.3.0.dist-info/METADATA
pytest_scenario_files-1.3.0.dist-info/WHEEL
pytest_scenario_files-1.3.0.dist-info/entry_points.txt
pytest_scenario_files-1.3.0.dist-info/licenses/LICENSE
pytest_scenario_files-1.3.0.dist-info/RECORD
