Metadata-Version: 2.4
Name: pytest-scenario-files
Version: 1.3.0
Summary: A pytest plugin that generates unit test scenarios from data files.
Project-URL: Documentation, https://pytest-scenario-files.mspex.net/
Project-URL: Repository, https://github.com/paulsuh/pytest-scenario-files
Project-URL: Issues, https://github.com/paulsuh/pytest-scenario-files/issues
Project-URL: Changelog, https://github.com/paulsuh/pytest-scenario-files/blob/main/CHANGES.md
Author-email: Paul Suh <paul@mspex.net>
License-File: LICENSE
Classifier: Development Status :: 5 - Production/Stable
Classifier: Framework :: Pytest
Classifier: Intended Audience :: Developers
Classifier: License :: OSI Approved :: MIT License
Classifier: Operating System :: OS Independent
Classifier: Programming Language :: Python
Classifier: Programming Language :: Python :: 3
Classifier: Programming Language :: Python :: 3 :: Only
Classifier: Programming Language :: Python :: 3.9
Classifier: Programming Language :: Python :: 3.10
Classifier: Programming Language :: Python :: 3.11
Classifier: Programming Language :: Python :: 3.12
Classifier: Programming Language :: Python :: 3.13
Classifier: Programming Language :: Python :: Implementation :: CPython
Classifier: Topic :: Software Development :: Testing
Requires-Python: >=3.9
Requires-Dist: pytest<9,>=7.4
Requires-Dist: pyyaml<7
Provides-Extra: precommit
Requires-Dist: ruff; extra == 'precommit'
Provides-Extra: responses
Requires-Dist: responses<1; extra == 'responses'
Provides-Extra: respx
Requires-Dist: respx<1; extra == 'respx'
Provides-Extra: unittest
Requires-Dist: pytest; extra == 'unittest'
Requires-Dist: pytest-cov; extra == 'unittest'
